jinjalint/__init__.py
jinjalint/__main__.py
jinjalint/_version.py
jinjalint/ast.py
jinjalint/check.py
jinjalint/cli.py
jinjalint/config.py
jinjalint/file.py
jinjalint/issue.py
jinjalint/lint.py
jinjalint/parse.py
jinjalint/parse_test.py
jinjalint/test.py
jinjalint/util.py
jinjalint/util_test.py
jinjalint-0.1.dist-info/DESCRIPTION.rst
jinjalint-0.1.dist-info/METADATA
jinjalint-0.1.dist-info/RECORD
jinjalint-0.1.dist-info/WHEEL
jinjalint-0.1.dist-info/entry_points.txt
jinjalint-0.1.dist-info/metadata.json
jinjalint-0.1.dist-info/top_level.txt
