Metadata-Version: 2.0
Name: jinjalint
Version: 0.1
Summary: A linter for Jinja-like templates
Home-page: UNKNOWN
Author: UNKNOWN
Author-email: UNKNOWN
License: MIT
Platform: UNKNOWN
Classifier: Development Status :: 3 - Alpha
Classifier: License :: OSI Approved :: MIT License
Classifier: Intended Audience :: Developers
Classifier: Programming Language :: Python :: 3.5
Classifier: Programming Language :: Python :: 3.6
Classifier: Programming Language :: Python :: 3.7
Requires-Dist: attrs (==17.2.0)
Requires-Dist: docopt (==0.6.2)
Requires-Dist: parsy (==1.1.0)
